spacetraders/__init__.py
spacetraders/api/__init__.py
spacetraders/api/agents/__init__.py
spacetraders/api/agents/get_my_agent.py
spacetraders/api/contracts/__init__.py
spacetraders/api/contracts/accept_contract.py
spacetraders/api/contracts/deliver_contract.py
spacetraders/api/contracts/fulfill_contract.py
spacetraders/api/contracts/get_contract.py
spacetraders/api/contracts/get_contracts.py
spacetraders/api/default/__init__.py
spacetraders/api/default/register.py
spacetraders/api/factions/__init__.py
spacetraders/api/factions/get_faction.py
spacetraders/api/factions/get_factions.py
spacetraders/api/fleet/__init__.py
spacetraders/api/fleet/create_chart.py
spacetraders/api/fleet/create_ship_ship_scan.py
spacetraders/api/fleet/create_ship_system_scan.py
spacetraders/api/fleet/create_ship_waypoint_scan.py
spacetraders/api/fleet/create_survey.py
spacetraders/api/fleet/dock_ship.py
spacetraders/api/fleet/extract_resources.py
spacetraders/api/fleet/get_my_ship.py
spacetraders/api/fleet/get_my_ship_cargo.py
spacetraders/api/fleet/get_my_ships.py
spacetraders/api/fleet/get_ship_cooldown.py
spacetraders/api/fleet/get_ship_nav.py
spacetraders/api/fleet/jettison.py
spacetraders/api/fleet/jump_ship.py
spacetraders/api/fleet/navigate_ship.py
spacetraders/api/fleet/orbit_ship.py
spacetraders/api/fleet/patch_ship_nav.py
spacetraders/api/fleet/purchase_cargo.py
spacetraders/api/fleet/purchase_ship.py
spacetraders/api/fleet/refuel_ship.py
spacetraders/api/fleet/sell_cargo.py
spacetraders/api/fleet/ship_refine.py
spacetraders/api/fleet/transfer_cargo.py
spacetraders/api/fleet/warp_ship.py
spacetraders/api/systems/__init__.py
spacetraders/api/systems/get_jump_gate.py
spacetraders/api/systems/get_market.py
spacetraders/api/systems/get_shipyard.py
spacetraders/api/systems/get_system.py
spacetraders/api/systems/get_system_waypoints.py
spacetraders/api/systems/get_systems.py
spacetraders/api/systems/get_waypoint.py
spacetraders/client.py
spacetraders/errors.py
python_spacetraders-0.1.0.dist-info/METADATA
python_spacetraders-0.1.0.dist-info/WHEEL
python_spacetraders-0.1.0.dist-info/RECORD
