Metadata-Version: 2.1
Name: python-spacetraders
Version: 0.1.0
Summary: Python API for Space Traders
License: Apache-2.0
Author: Marco Ceppi
Author-email: marco@ceppi.net
Requires-Python: >=3.11,<4.0
Classifier: License :: OSI Approved :: Apache Software License
Classifier: Programming Language :: Python :: 3
Classifier: Programming Language :: Python :: 3.11
Requires-Dist: httpx (>=0.24.0,<0.25.0)
